solar_angles/__init__.py
solar_angles/solar.py
solar_angles-0.26.dist-info/LICENSE
solar_angles-0.26.dist-info/METADATA
solar_angles-0.26.dist-info/WHEEL
solar_angles-0.26.dist-info/top_level.txt
solar_angles-0.26.dist-info/RECORD
