Metadata-Version: 2.1
Name: solar_angles
Version: 0.26
Summary: Quick solar_angles angle calculation package
Home-page: https://github.com/Myoldmopar/SolarCalculations
Author: Edwin Lee
License: ModifiedBSD
Keywords: Solar Angles,Building Simulation,Whole Building Energy Simulation,Heat Transfer,Modeling
Platform: Linux (Tested on Ubuntu)
Platform: MacOSX
Platform: Windows
Classifier: Development Status :: 4 - Beta
Classifier: Intended Audience :: Science/Research
Classifier: Natural Language :: English
Classifier: Operating System :: OS Independent
Classifier: Programming Language :: Python :: 3 :: Only
Classifier: Topic :: Scientific/Engineering
Classifier: Topic :: Scientific/Engineering :: Physics
Classifier: Topic :: Utilities
License-File: LICENSE
Requires-Dist: matplotlib
